ticko/__init__.py
ticko/decorators.py
ticko/py.typed
ticko/stop_watch.py
ticko-1.0.0.dist-info/WHEEL
ticko-1.0.0.dist-info/METADATA
ticko-1.0.0.dist-info/RECORD
