Metadata-Version: 2.3
Name: ticko
Version: 1.0.0
Summary: Thread-safe stopwatch for measuring elapsed time
Keywords: stopwatch,timer,performance,profiling,benchmark
Author: NakuRei
Author-email: NakuRei <nakurei7901@gmail.com>
Classifier: Development Status :: 4 - Beta
Classifier: Intended Audience :: Developers
Classifier: License :: OSI Approved :: MIT License
Classifier: Programming Language :: Python :: 3
Classifier: Programming Language :: Python :: 3.10
Classifier: Programming Language :: Python :: 3.11
Classifier: Programming Language :: Python :: 3.12
Classifier: Programming Language :: Python :: 3.13
Classifier: Topic :: Software Development :: Libraries :: Python Modules
Classifier: Topic :: System :: Benchmark
Classifier: Typing :: Typed
Requires-Python: >=3.10
Project-URL: Homepage, https://github.com/NakuRei/ticko
Project-URL: Issues, https://github.com/NakuRei/ticko/issues
Project-URL: Repository, https://github.com/NakuRei/ticko
